dmete/NationalAutomaticStations.txt
dmete/__init__.py
dmete/__main__.py
dmete/dump.py
dmete-1.1.0.dist-info/METADATA
dmete-1.1.0.dist-info/RECORD
dmete-1.1.0.dist-info/WHEEL
dmete-1.1.0.dist-info/entry_points.txt
dmete-1.1.0.dist-info/top_level.txt
