Metadata-Version: 2.1
Name: dmete
Version: 1.1.0
Summary: download mete data
Home-page: http://10.110.18.201:3000/Course/dump_mete
Author: Linhong Xiao
Author-email: xiaoforest@lzb.ac.cn
License: UNKNOWN
Platform: UNKNOWN
Classifier: Programming Language :: Python :: 3
Classifier: License :: OSI Approved :: MIT License
Classifier: Operating System :: OS Independent
